pollination/sandbox_solar_irradiance/__init__.py
pollination/sandbox_solar_irradiance/_irradiance_calc.py
pollination/sandbox_solar_irradiance/_raytracing.py
pollination/sandbox_solar_irradiance/entry.py
pollination_sandbox_solar_irradiance-0.2.1.dist-info/METADATA
pollination_sandbox_solar_irradiance-0.2.1.dist-info/WHEEL
pollination_sandbox_solar_irradiance-0.2.1.dist-info/top_level.txt
pollination_sandbox_solar_irradiance-0.2.1.dist-info/RECORD
