Metadata-Version: 2.1
Name: pollination-sandbox-solar-irradiance
Version: 0.2.1
Summary: A recipe to assess average solar irradiance beneath Sandbox Solar agrivoltaic panels.
Home-page: https://github.com/pollination/sandbox-solar-irradiance
Author: ladybug-tools
Author-email: info@ladybug.tools
Maintainer: mostapha, ladybug-tools
Maintainer-email: mostapha@ladybug.tools, info@ladybug.tools
License: PolyForm Shield License 1.0.0, https://polyformproject.org/wp-content/uploads/2020/06/PolyForm-Shield-1.0.0.txt
Project-URL: icon, https://raw.githubusercontent.com/ladybug-tools/artwork/master/icons_components/ladybug/png/incidentrad.png
Project-URL: docker, https://hub.docker.com/r/ladybugtools/honeybee-radiance
Keywords: honeybee,radiance,ladybug-tools,daylight,sandbox-solar-irradiance
Requires-Dist: pollination-honeybee-radiance (>=0.22.63)
Requires-Dist: pollination-path (>=0.3.0)
Requires-Dist: pollination-alias (>=0.9.12)
